Workbook

Sheet Precios de venta
A1: Marca | B1: Referencia | C1: Producto en la tienda | D1: Costo proveedor (USD) | E1: Costo puesto en depósito | F1: Costo + envío al cliente | G1: Precio mínimo (ganancia ≥ piso) | H1: Precio objetivo | I1: Precio de la calle (mercado) | J1: PRECIO DE VENTA 1 filtro | K1: Ganancia por filtro (USD) | L1: Margen % | M1: Precio paquete de 2 | N1: Ganancia paquete (USD) | O1: Veredicto | P1: Precios vistos en el mercado | Q1: Fuente | R1: Cartón | S1: Nota del proveedor
A2: Samsung | B2: DA29-00003F / HA-FIN1 | D2: 19 | E2: =D2*(1+Supuestos!$B$4) | F2: =E2+Supuestos!$B$5 | G2: =ROUNDUP((F2+Supuestos!$B$3+Supuestos!$B$9)/(1-Supuestos!$B$2),0)-0.01 | H2: =ROUNDUP(MAX((F2+Supuestos!$B$3)/(1-Supuestos!$B$2-Supuestos!$B$8),(F2+Supuestos!$B$3+Supuestos!$B$7)/(1-Supuestos!$B$2)),0)-0.01 | J2: 36.99 | K2: =J2-J2*Supuestos!$B$2-Supuestos!$B$3-F2 | L2: =K2/J2 | M2: =ROUNDUP(MAX(2*J2*0.92,(2*E2+Supuestos!$B$6+Supuestos!$B$3+8)/(1-Supuestos!$B$2)),0)-0.01 | N2: =M2-M2*Supuestos!$B$2-Supuestos!$B$3-2*E2-Supuestos!$B$6 | O2: Sin precio de mercado: precio objetivo | P2: Sin datos de mercado | R2: 30
A3: Samsung | B3: DA29-00003G / HAF-CU1 / HAF-FIN2 | C3: sam-cu1-o | D3: 24.5 | E3: =D3*(1+Supuestos!$B$4) | F3: =E3+Supuestos!$B$5 | G3: =ROUNDUP((F3+Supuestos!$B$3+Supuestos!$B$9)/(1-Supuestos!$B$2),0)-0.01 | H3: =ROUNDUP(MAX((F3+Supuestos!$B$3)/(1-Supuestos!$B$2-Supuestos!$B$8),(F3+Supuestos!$B$3+Supuestos!$B$7)/(1-Supuestos!$B$2)),0)-0.01 | J3: 43.99 | K3: =J3-J3*Supuestos!$B$2-Supuestos!$B$3-F3 | L3: =K3/J3 | M3: =ROUNDUP(MAX(2*J3*0.92,(2*E3+Supuestos!$B$6+Supuestos!$B$3+8)/(1-Supuestos!$B$2)),0)-0.01 | N3: =M3-M3*Supuestos!$B$2-Supuestos!$B$3-2*E3-Supuestos!$B$6 | O3: Sin precio de mercado: precio objetivo | P3: Sin datos de mercado | R3: 6
A4: Samsung | B4: DA29-00020B / HAF-CIN | C4: sam-cin-o | D4: 23.5 | E4: =D4*(1+Supuestos!$B$4) | F4: =E4+Supuestos!$B$5 | G4: =ROUNDUP((F4+Supuestos!$B$3+Supuestos!$B$9)/(1-Supuestos!$B$2),0)-0.01 | H4: =ROUNDUP(MAX((F4+Supuestos!$B$3)/(1-Supuestos!$B$2-Supuestos!$B$8),(F4+Supuestos!$B$3+Supuestos!$B$7)/(1-Supuestos!$B$2)),0)-0.01 | I4: 34.99 | O4: No vender suelto: el mercado está casi al precio de costo | P4: Lista 59.99; Allfilters 34.99; eBay desde 18.99 | Q4: allfilters.com, ebay.com | R4: 6
A5: Samsung | B5: DA97-17376B / HAF-QIN | C5: sam-qin-o | D5: 25.5 | E5: =D5*(1+Supuestos!$B$4) | F5: =E5+Supuestos!$B$5 | G5: =ROUNDUP((F5+Supuestos!$B$3+Supuestos!$B$9)/(1-Supuestos!$B$2),0)-0.01 | H5: =ROUNDUP(MAX((F5+Supuestos!$B$3)/(1-Supuestos!$B$2-Supuestos!$B$8),(F5+Supuestos!$B$3+Supuestos!$B$7)/(1-Supuestos!$B$2)),0)-0.01 | I5: 36.99 | O5: No vender suelto: el mercado está casi al precio de costo | P5: Genuino 34–44; Allfilters 36.99; terceros 28.99 por 3 | Q5: allfilters.com, slickdeals.net | R5: 6
A6: Samsung | B6: DA29-10105J / HAF-EX | C6: sam-ex-o | D6: 9.5 | E6: =D6*(1+Supuestos!$B$4) | F6: =E6+Supuestos!$B$5 | G6: =ROUNDUP((F6+Supuestos!$B$3+Supuestos!$B$9)/(1-Supuestos!$B$2),0)-0.01 | H6: =ROUNDUP(MAX((F6+Supuestos!$B$3)/(1-Supuestos!$B$2-Supuestos!$B$8),(F6+Supuestos!$B$3+Supuestos!$B$7)/(1-Supuestos!$B$2)),0)-0.01 | I6: 19 | O6: No vender suelto: el mercado está casi al precio de costo | P6: eBay 15–18 + envío; filtro en línea 4378411RB a 23.49 (Slyman) | Q6: ebay, slymanbros.com | R6: 25
A7: LG | B7: LT1000P | C7: lg-1000-o | D7: 37.75 | E7: =D7*(1+Supuestos!$B$4) | F7: =E7+Supuestos!$B$5 | G7: =ROUNDUP((F7+Supuestos!$B$3+Supuestos!$B$9)/(1-Supuestos!$B$2),0)-0.01 | H7: =ROUNDUP(MAX((F7+Supuestos!$B$3)/(1-Supuestos!$B$2-Supuestos!$B$8),(F7+Supuestos!$B$3+Supuestos!$B$7)/(1-Supuestos!$B$2)),0)-0.01 | I7: 54.99 | J7: 61.99 | K7: =J7-J7*Supuestos!$B$2-Supuestos!$B$3-F7 | L7: =K7/J7 | M7: =ROUNDUP(MAX(2*J7*0.92,(2*E7+Supuestos!$B$6+Supuestos!$B$3+8)/(1-Supuestos!$B$2)),0)-0.01 | N7: =M7-M7*Supuestos!$B$2-Supuestos!$B$3-2*E7-Supuestos!$B$6 | O7: Competitivo | P7: Genuino 54.99; terceros desde 12.95 | Q7: allfilters.com, star-power.com | R7: 36
A8: LG | B8: LT800P | C8: lg-800-o | D8: 36.5 | E8: =D8*(1+Supuestos!$B$4) | F8: =E8+Supuestos!$B$5 | G8: =ROUNDUP((F8+Supuestos!$B$3+Supuestos!$B$9)/(1-Supuestos!$B$2),0)-0.01 | H8: =ROUNDUP(MAX((F8+Supuestos!$B$3)/(1-Supuestos!$B$2-Supuestos!$B$8),(F8+Supuestos!$B$3+Supuestos!$B$7)/(1-Supuestos!$B$2)),0)-0.01 | I8: 54.97 | J8: 59.99 | K8: =J8-J8*Supuestos!$B$2-Supuestos!$B$3-F8 | L8: =K8/J8 | M8: =ROUNDUP(MAX(2*J8*0.92,(2*E8+Supuestos!$B$6+Supuestos!$B$3+8)/(1-Supuestos!$B$2)),0)-0.01 | N8: =M8-M8*Supuestos!$B$2-Supuestos!$B$3-2*E8-Supuestos!$B$6 | O8: Competitivo | P8: PC Richard 54.97 | Q8: pcrichard.com | R8: 49
A9: LG | B9: LT700P | C9: lg-700-o | D9: 36.5 | E9: =D9*(1+Supuestos!$B$4) | F9: =E9+Supuestos!$B$5 | G9: =ROUNDUP((F9+Supuestos!$B$3+Supuestos!$B$9)/(1-Supuestos!$B$2),0)-0.01 | H9: =ROUNDUP(MAX((F9+Supuestos!$B$3)/(1-Supuestos!$B$2-Supuestos!$B$8),(F9+Supuestos!$B$3+Supuestos!$B$7)/(1-Supuestos!$B$2)),0)-0.01 | I9: 49.99 | J9: 54.99 | K9: =J9-J9*Supuestos!$B$2-Supuestos!$B$3-F9 | L9: =K9/J9 | M9: =ROUNDUP(MAX(2*J9*0.92,(2*E9+Supuestos!$B$6+Supuestos!$B$3+8)/(1-Supuestos!$B$2)),0)-0.01 | N9: =M9-M9*Supuestos!$B$2-Supuestos!$B$3-2*E9-Supuestos!$B$6 | O9: Ganancia justa: igualar al mercado | P9: Walmart 50.99; Atomic 44.95; genérico 11–25 | Q9: walmart.com, atomicfilters.com | R9: 36
A10: LG | B10: LT700P without T code | D10: 24.5 | E10: =D10*(1+Supuestos!$B$4) | F10: =E10+Supuestos!$B$5 | G10: =ROUNDUP((F10+Supuestos!$B$3+Supuestos!$B$9)/(1-Supuestos!$B$2),0)-0.01 | H10: =ROUNDUP(MAX((F10+Supuestos!$B$3)/(1-Supuestos!$B$2-Supuestos!$B$8),(F10+Supuestos!$B$3+Supuestos!$B$7)/(1-Supuestos!$B$2)),0)-0.01 | J10: 43.99 | K10: =J10-J10*Supuestos!$B$2-Supuestos!$B$3-F10 | L10: =K10/J10 | M10: =ROUNDUP(MAX(2*J10*0.92,(2*E10+Supuestos!$B$6+Supuestos!$B$3+8)/(1-Supuestos!$B$2)),0)-0.01 | N10: =M10-M10*Supuestos!$B$2-Supuestos!$B$3-2*E10-Supuestos!$B$6 | O10: Sin precio de mercado: precio objetivo | P10: Sin datos de mercado | R10: 36 | S10: Variante sin código T: confirma con el proveedor qué significa antes de venderla como LG.
A11: LG | B11: LT600P | C11: lg-600-o | D11: 36.5 | E11: =D11*(1+Supuestos!$B$4) | F11: =E11+Supuestos!$B$5 | G11: =ROUNDUP((F11+Supuestos!$B$3+Supuestos!$B$9)/(1-Supuestos!$B$2),0)-0.01 | H11: =ROUNDUP(MAX((F11+Supuestos!$B$3)/(1-Supuestos!$B$2-Supuestos!$B$8),(F11+Supuestos!$B$3+Supuestos!$B$7)/(1-Supuestos!$B$2)),0)-0.01 | J11: 59.99 | K11: =J11-J11*Supuestos!$B$2-Supuestos!$B$3-F11 | L11: =K11/J11 | M11: =ROUNDUP(MAX(2*J11*0.92,(2*E11+Supuestos!$B$6+Supuestos!$B$3+8)/(1-Supuestos!$B$2)),0)-0.01 | N11: =M11-M11*Supuestos!$B$2-Supuestos!$B$3-2*E11-Supuestos!$B$6 | O11: Sin precio de mercado: precio objetivo | P11: Sin datos de mercado | R11: 24
A12: LG | B12: LT500P | C12: lg-500-o | D12: 34 | E12: =D12*(1+Supuestos!$B$4) | F12: =E12+Supuestos!$B$5 | G12: =ROUNDUP((F12+Supuestos!$B$3+Supuestos!$B$9)/(1-Supuestos!$B$2),0)-0.01 | H12: =ROUNDUP(MAX((F12+Supuestos!$B$3)/(1-Supuestos!$B$2-Supuestos!$B$8),(F12+Supuestos!$B$3+Supuestos!$B$7)/(1-Supuestos!$B$2)),0)-0.01 | I12: 54.99 | J12: 55.99 | K12: =J12-J12*Supuestos!$B$2-Supuestos!$B$3-F12 | L12: =K12/J12 | M12: =ROUNDUP(MAX(2*J12*0.92,(2*E12+Supuestos!$B$6+Supuestos!$B$3+8)/(1-Supuestos!$B$2)),0)-0.01 | N12: =M12-M12*Supuestos!$B$2-Supuestos!$B$3-2*E12-Supuestos!$B$6 | O12: Competitivo | P12: Allfilters 54.99; terceros 12.95 | Q12: allfilters.com | R12: 36
A13: LG | B13: ADQ73693903 / FSS-002 | C13: lg-ex-o | D13: 9.5 | E13: =D13*(1+Supuestos!$B$4) | F13: =E13+Supuestos!$B$5 | G13: =ROUNDUP((F13+Supuestos!$B$3+Supuestos!$B$9)/(1-Supuestos!$B$2),0)-0.01 | H13: =ROUNDUP(MAX((F13+Supuestos!$B$3)/(1-Supuestos!$B$2-Supuestos!$B$8),(F13+Supuestos!$B$3+Supuestos!$B$7)/(1-Supuestos!$B$2)),0)-0.01 | J13: 25.99 | K13: =J13-J13*Supuestos!$B$2-Supuestos!$B$3-F13 | L13: =K13/J13 | M13: =ROUNDUP(MAX(2*J13*0.92,(2*E13+Supuestos!$B$6+Supuestos!$B$3+8)/(1-Supuestos!$B$2)),0)-0.01 | N13: =M13-M13*Supuestos!$B$2-Supuestos!$B$3-2*E13-Supuestos!$B$6 | O13: Sin precio de mercado: precio objetivo | P13: Sin datos de mercado | R13: 36
A14: LG | B14: LT120F / ADQ73334008 | D14: 18.5 | E14: =D14*(1+Supuestos!$B$4) | F14: =E14+Supuestos!$B$5 | G14: =ROUNDUP((F14+Supuestos!$B$3+Supuestos!$B$9)/(1-Supuestos!$B$2),0)-0.01 | H14: =ROUNDUP(MAX((F14+Supuestos!$B$3)/(1-Supuestos!$B$2-Supuestos!$B$8),(F14+Supuestos!$B$3+Supuestos!$B$7)/(1-Supuestos!$B$2)),0)-0.01 | J14: 35.99 | K14: =J14-J14*Supuestos!$B$2-Supuestos!$B$3-F14 | L14: =K14/J14 | M14: =ROUNDUP(MAX(2*J14*0.92,(2*E14+Supuestos!$B$6+Supuestos!$B$3+8)/(1-Supuestos!$B$2)),0)-0.01 | N14: =M14-M14*Supuestos!$B$2-Supuestos!$B$3-2*E14-Supuestos!$B$6 | O14: Sin precio de mercado: precio objetivo | P14: Sin datos de mercado | R14: 100
A15: GE | B15: MWF | C15: ge-mwf-o | D15: 39 | E15: =D15*(1+Supuestos!$B$4) | F15: =E15+Supuestos!$B$5 | G15: =ROUNDUP((F15+Supuestos!$B$3+Supuestos!$B$9)/(1-Supuestos!$B$2),0)-0.01 | H15: =ROUNDUP(MAX((F15+Supuestos!$B$3)/(1-Supuestos!$B$2-Supuestos!$B$8),(F15+Supuestos!$B$3+Supuestos!$B$7)/(1-Supuestos!$B$2)),0)-0.01 | I15: 45 | O15: No vender suelto: el mercado está casi al precio de costo | P15: Genuino 36–50 (Sears 37.14; Walmart 35.99; Allfilters 45.99) | Q15: searspartsdirect.com, allfilters.com | R15: 6
A16: GE | B16: XWFE | D16: 43 | E16: =D16*(1+Supuestos!$B$4) | F16: =E16+Supuestos!$B$5 | G16: =ROUNDUP((F16+Supuestos!$B$3+Supuestos!$B$9)/(1-Supuestos!$B$2),0)-0.01 | H16: =ROUNDUP(MAX((F16+Supuestos!$B$3)/(1-Supuestos!$B$2-Supuestos!$B$8),(F16+Supuestos!$B$3+Supuestos!$B$7)/(1-Supuestos!$B$2)),0)-0.01 | J16: 68.99 | K16: =J16-J16*Supuestos!$B$2-Supuestos!$B$3-F16 | L16: =K16/J16 | M16: =ROUNDUP(MAX(2*J16*0.92,(2*E16+Supuestos!$B$6+Supuestos!$B$3+8)/(1-Supuestos!$B$2)),0)-0.01 | N16: =M16-M16*Supuestos!$B$2-Supuestos!$B$3-2*E16-Supuestos!$B$6 | O16: Sin precio de mercado: precio objetivo | P16: Solo genéricos a 18–25; sin precio del genuino | Q16: walmart.com | R16: 4 | S16: Tu tienda de Colombia vende el XWF (no es igual al XWFE): confirma cuál vas a vender.
A17: GE | B17: RPWFE | D17: 43 | E17: =D17*(1+Supuestos!$B$4) | F17: =E17+Supuestos!$B$5 | G17: =ROUNDUP((F17+Supuestos!$B$3+Supuestos!$B$9)/(1-Supuestos!$B$2),0)-0.01 | H17: =ROUNDUP(MAX((F17+Supuestos!$B$3)/(1-Supuestos!$B$2-Supuestos!$B$8),(F17+Supuestos!$B$3+Supuestos!$B$7)/(1-Supuestos!$B$2)),0)-0.01 | J17: 68.99 | K17: =J17-J17*Supuestos!$B$2-Supuestos!$B$3-F17 | L17: =K17/J17 | M17: =ROUNDUP(MAX(2*J17*0.92,(2*E17+Supuestos!$B$6+Supuestos!$B$3+8)/(1-Supuestos!$B$2)),0)-0.01 | N17: =M17-M17*Supuestos!$B$2-Supuestos!$B$3-2*E17-Supuestos!$B$6 | O17: Sin precio de mercado: precio objetivo | P17: Sin datos de mercado | R17: 4
A18: GE | B18: AFPWF | D18: 34 | E18: =D18*(1+Supuestos!$B$4) | F18: =E18+Supuestos!$B$5 | G18: =ROUNDUP((F18+Supuestos!$B$3+Supuestos!$B$9)/(1-Supuestos!$B$2),0)-0.01 | H18: =ROUNDUP(MAX((F18+Supuestos!$B$3)/(1-Supuestos!$B$2-Supuestos!$B$8),(F18+Supuestos!$B$3+Supuestos!$B$7)/(1-Supuestos!$B$2)),0)-0.01 | J18: 55.99 | K18: =J18-J18*Supuestos!$B$2-Supuestos!$B$3-F18 | L18: =K18/J18 | M18: =ROUNDUP(MAX(2*J18*0.92,(2*E18+Supuestos!$B$6+Supuestos!$B$3+8)/(1-Supuestos!$B$2)),0)-0.01 | N18: =M18-M18*Supuestos!$B$2-Supuestos!$B$3-2*E18-Supuestos!$B$6 | O18: Sin precio de mercado: precio objetivo | P18: Sin datos de mercado | R18: 2
A19: GE | B19: FQ18MN | D19: 78.28 | E19: =D19*(1+Supuestos!$B$4) | F19: =E19+Supuestos!$B$5 | G19: =ROUNDUP((F19+Supuestos!$B$3+Supuestos!$B$9)/(1-Supuestos!$B$2),0)-0.01 | H19: =ROUNDUP(MAX((F19+Supuestos!$B$3)/(1-Supuestos!$B$2-Supuestos!$B$8),(F19+Supuestos!$B$3+Supuestos!$B$7)/(1-Supuestos!$B$2)),0)-0.01 | J19: 116.99 | K19: =J19-J19*Supuestos!$B$2-Supuestos!$B$3-F19 | L19: =K19/J19 | M19: =ROUNDUP(MAX(2*J19*0.92,(2*E19+Supuestos!$B$6+Supuestos!$B$3+8)/(1-Supuestos!$B$2)),0)-0.01 | N19: =M19-M19*Supuestos!$B$2-Supuestos!$B$3-2*E19-Supuestos!$B$6 | O19: Sin precio de mercado: precio objetivo | P19: Sin datos de mercado | R19: 2
A20: GE | B20: FQK1K | D20: 36 | E20: =D20*(1+Supuestos!$B$4) | F20: =E20+Supuestos!$B$5 | G20: =ROUNDUP((F20+Supuestos!$B$3+Supuestos!$B$9)/(1-Supuestos!$B$2),0)-0.01 | H20: =ROUNDUP(MAX((F20+Supuestos!$B$3)/(1-Supuestos!$B$2-Supuestos!$B$8),(F20+Supuestos!$B$3+Supuestos!$B$7)/(1-Supuestos!$B$2)),0)-0.01 | J20: 58.99 | K20: =J20-J20*Supuestos!$B$2-Supuestos!$B$3-F20 | L20: =K20/J20 | M20: =ROUNDUP(MAX(2*J20*0.92,(2*E20+Supuestos!$B$6+Supuestos!$B$3+8)/(1-Supuestos!$B$2)),0)-0.01 | N20: =M20-M20*Supuestos!$B$2-Supuestos!$B$3-2*E20-Supuestos!$B$6 | O20: Sin precio de mercado: precio objetivo | P20: Sin datos de mercado | R20: 2
A21: GE | B21: FQK2J | D21: 59.15 | E21: =D21*(1+Supuestos!$B$4) | F21: =E21+Supuestos!$B$5 | G21: =ROUNDUP((F21+Supuestos!$B$3+Supuestos!$B$9)/(1-Supuestos!$B$2),0)-0.01 | H21: =ROUNDUP(MAX((F21+Supuestos!$B$3)/(1-Supuestos!$B$2-Supuestos!$B$8),(F21+Supuestos!$B$3+Supuestos!$B$7)/(1-Supuestos!$B$2)),0)-0.01 | J21: 90.99 | K21: =J21-J21*Supuestos!$B$2-Supuestos!$B$3-F21 | L21: =K21/J21 | M21: =ROUNDUP(MAX(2*J21*0.92,(2*E21+Supuestos!$B$6+Supuestos!$B$3+8)/(1-Supuestos!$B$2)),0)-0.01 | N21: =M21-M21*Supuestos!$B$2-Supuestos!$B$3-2*E21-Supuestos!$B$6 | O21: Sin precio de mercado: precio objetivo | P21: Sin datos de mercado | R21: 2
A22: GE | B22: FQROPF | D22: 60.91 | E22: =D22*(1+Supuestos!$B$4) | F22: =E22+Supuestos!$B$5 | G22: =ROUNDUP((F22+Supuestos!$B$3+Supuestos!$B$9)/(1-Supuestos!$B$2),0)-0.01 | H22: =ROUNDUP(MAX((F22+Supuestos!$B$3)/(1-Supuestos!$B$2-Supuestos!$B$8),(F22+Supuestos!$B$3+Supuestos!$B$7)/(1-Supuestos!$B$2)),0)-0.01 | J22: 92.99 | K22: =J22-J22*Supuestos!$B$2-Supuestos!$B$3-F22 | L22: =K22/J22 | M22: =ROUNDUP(MAX(2*J22*0.92,(2*E22+Supuestos!$B$6+Supuestos!$B$3+8)/(1-Supuestos!$B$2)),0)-0.01 | N22: =M22-M22*Supuestos!$B$2-Supuestos!$B$3-2*E22-Supuestos!$B$6 | O22: Sin precio de mercado: precio objetivo | P22: Sin datos de mercado | R22: 1
A23: GE | B23: FQSVN | D23: 43.4 | E23: =D23*(1+Supuestos!$B$4) | F23: =E23+Supuestos!$B$5 | G23: =ROUNDUP((F23+Supuestos!$B$3+Supuestos!$B$9)/(1-Supuestos!$B$2),0)-0.01 | H23: =ROUNDUP(MAX((F23+Supuestos!$B$3)/(1-Supuestos!$B$2-Supuestos!$B$8),(F23+Supuestos!$B$3+Supuestos!$B$7)/(1-Supuestos!$B$2)),0)-0.01 | J23: 68.99 | K23: =J23-J23*Supuestos!$B$2-Supuestos!$B$3-F23 | L23: =K23/J23 | M23: =ROUNDUP(MAX(2*J23*0.92,(2*E23+Supuestos!$B$6+Supuestos!$B$3+8)/(1-Supuestos!$B$2)),0)-0.01 | N23: =M23-M23*Supuestos!$B$2-Supuestos!$B$3-2*E23-Supuestos!$B$6 | O23: Sin precio de mercado: precio objetivo | P23: Sin datos de mercado | R23: 2
A24: GE | B24: FTHLM | D24: 60.46 | E24: =D24*(1+Supuestos!$B$4) | F24: =E24+Supuestos!$B$5 | G24: =ROUNDUP((F24+Supuestos!$B$3+Supuestos!$B$9)/(1-Supuestos!$B$2),0)-0.01 | H24: =ROUNDUP(MAX((F24+Supuestos!$B$3)/(1-Supuestos!$B$2-Supuestos!$B$8),(F24+Supuestos!$B$3+Supuestos!$B$7)/(1-Supuestos!$B$2)),0)-0.01 | J24: 91.99 | K24: =J24-J24*Supuestos!$B$2-Supuestos!$B$3-F24 | L24: =K24/J24 | M24: =ROUNDUP(MAX(2*J24*0.92,(2*E24+Supuestos!$B$6+Supuestos!$B$3+8)/(1-Supuestos!$B$2)),0)-0.01 | N24: =M24-M24*Supuestos!$B$2-Supuestos!$B$3-2*E24-Supuestos!$B$6 | O24: Sin precio de mercado: precio objetivo | P24: Sin datos de mercado | R24: 2
A25: GE | B25: FTHTM | D25: 30.97 | E25: =D25*(1+Supuestos!$B$4) | F25: =E25+Supuestos!$B$5 | G25: =ROUNDUP((F25+Supuestos!$B$3+Supuestos!$B$9)/(1-Supuestos!$B$2),0)-0.01 | H25: =ROUNDUP(MAX((F25+Supuestos!$B$3)/(1-Supuestos!$B$2-Supuestos!$B$8),(F25+Supuestos!$B$3+Supuestos!$B$7)/(1-Supuestos!$B$2)),0)-0.01 | J25: 51.99 | K25: =J25-J25*Supuestos!$B$2-Supuestos!$B$3-F25 | L25: =K25/J25 | M25: =ROUNDUP(MAX(2*J25*0.92,(2*E25+Supuestos!$B$6+Supuestos!$B$3+8)/(1-Supuestos!$B$2)),0)-0.01 | N25: =M25-M25*Supuestos!$B$2-Supuestos!$B$3-2*E25-Supuestos!$B$6 | O25: Sin precio de mercado: precio objetivo | P25: Sin datos de mercado | R25: 2
A26: GE | B26: FX12M | D26: 60.46 | E26: =D26*(1+Supuestos!$B$4) | F26: =E26+Supuestos!$B$5 | G26: =ROUNDUP((F26+Supuestos!$B$3+Supuestos!$B$9)/(1-Supuestos!$B$2),0)-0.01 | H26: =ROUNDUP(MAX((F26+Supuestos!$B$3)/(1-Supuestos!$B$2-Supuestos!$B$8),(F26+Supuestos!$B$3+Supuestos!$B$7)/(1-Supuestos!$B$2)),0)-0.01 | J26: 91.99 | K26: =J26-J26*Supuestos!$B$2-Supuestos!$B$3-F26 | L26: =K26/J26 | M26: =ROUNDUP(MAX(2*J26*0.92,(2*E26+Supuestos!$B$6+Supuestos!$B$3+8)/(1-Supuestos!$B$2)),0)-0.01 | N26: =M26-M26*Supuestos!$B$2-Supuestos!$B$3-2*E26-Supuestos!$B$6 | O26: Sin precio de mercado: precio objetivo | P26: Sin datos de mercado | R26: 2
A27: GE | B27: FXHSC | D27: 20.31 | E27: =D27*(1+Supuestos!$B$4) | F27: =E27+Supuestos!$B$5 | G27: =ROUNDUP((F27+Supuestos!$B$3+Supuestos!$B$9)/(1-Supuestos!$B$2),0)-0.01 | H27: =ROUNDUP(MAX((F27+Supuestos!$B$3)/(1-Supuestos!$B$2-Supuestos!$B$8),(F27+Supuestos!$B$3+Supuestos!$B$7)/(1-Supuestos!$B$2)),0)-0.01 | J27: 37.99 | K27: =J27-J27*Supuestos!$B$2-Supuestos!$B$3-F27 | L27: =K27/J27 | M27: =ROUNDUP(MAX(2*J27*0.92,(2*E27+Supuestos!$B$6+Supuestos!$B$3+8)/(1-Supuestos!$B$2)),0)-0.01 | N27: =M27-M27*Supuestos!$B$2-Supuestos!$B$3-2*E27-Supuestos!$B$6 | O27: Sin precio de mercado: precio objetivo | P27: Sin datos de mercado | R27: 1
A28: GE | B28: FXHTC | D28: 33.09 | E28: =D28*(1+Supuestos!$B$4) | F28: =E28+Supuestos!$B$5 | G28: =ROUNDUP((F28+Supuestos!$B$3+Supuestos!$B$9)/(1-Supuestos!$B$2),0)-0.01 | H28: =ROUNDUP(MAX((F28+Supuestos!$B$3)/(1-Supuestos!$B$2-Supuestos!$B$8),(F28+Supuestos!$B$3+Supuestos!$B$7)/(1-Supuestos!$B$2)),0)-0.01 | J28: 54.99 | K28: =J28-J28*Supuestos!$B$2-Supuestos!$B$3-F28 | L28: =K28/J28 | M28: =ROUNDUP(MAX(2*J28*0.92,(2*E28+Supuestos!$B$6+Supuestos!$B$3+8)/(1-Supuestos!$B$2)),0)-0.01 | N28: =M28-M28*Supuestos!$B$2-Supuestos!$B$3-2*E28-Supuestos!$B$6 | O28: Sin precio de mercado: precio objetivo | P28: Sin datos de mercado | R28: 2
... A50: Frigidaire | B50: PAULTRA2 | D50: 14 | E50: =D50*(1+Supuestos!$B$4) | F50: =E50+Supuestos!$B$5 | G50: =ROUNDUP((F50+Supuestos!$B$3+Supuestos!$B$9)/(1-Supuestos!$B$2),0)-0.01 | H50: =ROUNDUP(MAX((F50+Supuestos!$B$3)/(1-Supuestos!$B$2-Supuestos!$B$8),(F50+Supuestos!$B$3+Supuestos!$B$7)/(1-Supuestos!$B$2)),0)-0.01 | J50: 30.99 | K50: =J50-J50*Supuestos!$B$2-Supuestos!$B$3-F50 | L50: =K50/J50 | M50: =ROUNDUP(MAX(2*J50*0.92,(2*E50+Supuestos!$B$6+Supuestos!$B$3+8)/(1-Supuestos!$B$2)),0)-0.01 | N50: =M50-M50*Supuestos!$B$2-Supuestos!$B$3-2*E50-Supuestos!$B$6 | O50: Sin precio de mercado: precio objetivo | P50: Sin datos de mercado | R50: 6
A51: Frigidaire | B51: PAULTRA2PK | D51: 22.47 | E51: =D51*(1+Supuestos!$B$4) | F51: =E51+Supuestos!$B$5 | G51: =ROUNDUP((F51+Supuestos!$B$3+Supuestos!$B$9)/(1-Supuestos!$B$2),0)-0.01 | H51: =ROUNDUP(MAX((F51+Supuestos!$B$3)/(1-Supuestos!$B$2-Supuestos!$B$8),(F51+Supuestos!$B$3+Supuestos!$B$7)/(1-Supuestos!$B$2)),0)-0.01 | J51: 40.99 | K51: =J51-J51*Supuestos!$B$2-Supuestos!$B$3-F51 | L51: =K51/J51 | M51: =ROUNDUP(MAX(2*J51*0.92,(2*E51+Supuestos!$B$6+Supuestos!$B$3+8)/(1-Supuestos!$B$2)),0)-0.01 | N51: =M51-M51*Supuestos!$B$2-Supuestos!$B$3-2*E51-Supuestos!$B$6 | O51: Sin precio de mercado: precio objetivo | P51: Sin datos de mercado
A52: Frigidaire | B52: PAULTRA4PK | D52: 35.67 | E52: =D52*(1+Supuestos!$B$4) | F52: =E52+Supuestos!$B$5 | G52: =ROUNDUP((F52+Supuestos!$B$3+Supuestos!$B$9)/(1-Supuestos!$B$2),0)-0.01 | H52: =ROUNDUP(MAX((F52+Supuestos!$B$3)/(1-Supuestos!$B$2-Supuestos!$B$8),(F52+Supuestos!$B$3+Supuestos!$B$7)/(1-Supuestos!$B$2)),0)-0.01 | J52: 58.99 | K52: =J52-J52*Supuestos!$B$2-Supuestos!$B$3-F52 | L52: =K52/J52 | M52: =ROUNDUP(MAX(2*J52*0.92,(2*E52+Supuestos!$B$6+Supuestos!$B$3+8)/(1-Supuestos!$B$2)),0)-0.01 | N52: =M52-M52*Supuestos!$B$2-Supuestos!$B$3-2*E52-Supuestos!$B$6 | O52: Sin precio de mercado: precio objetivo | P52: Sin datos de mercado
A53: Frigidaire | B53: PAULTRAII2PK | D53: 22.48 | E53: =D53*(1+Supuestos!$B$4) | F53: =E53+Supuestos!$B$5 | G53: =ROUNDUP((F53+Supuestos!$B$3+Supuestos!$B$9)/(1-Supuestos!$B$2),0)-0.01 | H53: =ROUNDUP(MAX((F53+Supuestos!$B$3)/(1-Supuestos!$B$2-Supuestos!$B$8),(F53+Supuestos!$B$3+Supuestos!$B$7)/(1-Supuestos!$B$2)),0)-0.01 | J53: 40.99 | K53: =J53-J53*Supuestos!$B$2-Supuestos!$B$3-F53 | L53: =K53/J53 | M53: =ROUNDUP(MAX(2*J53*0.92,(2*E53+Supuestos!$B$6+Supuestos!$B$3+8)/(1-Supuestos!$B$2)),0)-0.01 | N53: =M53-M53*Supuestos!$B$2-Supuestos!$B$3-2*E53-Supuestos!$B$6 | O53: Sin precio de mercado: precio objetivo | P53: Sin datos de mercado
A54: Frigidaire | B54: AFCB | D54: 12.65 | E54: =D54*(1+Supuestos!$B$4) | F54: =E54+Supuestos!$B$5 | G54: =ROUNDUP((F54+Supuestos!$B$3+Supuestos!$B$9)/(1-Supuestos!$B$2),0)-0.01 | H54: =ROUNDUP(MAX((F54+Supuestos!$B$3)/(1-Supuestos!$B$2-Supuestos!$B$8),(F54+Supuestos!$B$3+Supuestos!$B$7)/(1-Supuestos!$B$2)),0)-0.01 | J54: 29.99 | K54: =J54-J54*Supuestos!$B$2-Supuestos!$B$3-F54 | L54: =K54/J54 | M54: =ROUNDUP(MAX(2*J54*0.92,(2*E54+Supuestos!$B$6+Supuestos!$B$3+8)/(1-Supuestos!$B$2)),0)-0.01 | N54: =M54-M54*Supuestos!$B$2-Supuestos!$B$3-2*E54-Supuestos!$B$6 | O54: Sin precio de mercado: precio objetivo | P54: Sin datos de mercado
A55: Frigidaire | B55: TMFRGPAAF1KT | D55: 16.23 | E55: =D55*(1+Supuestos!$B$4) | F55: =E55+Supuestos!$B$5 | G55: =ROUNDUP((F55+Supuestos!$B$3+Supuestos!$B$9)/(1-Supuestos!$B$2),0)-0.01 | H55: =ROUNDUP(MAX((F55+Supuestos!$B$3)/(1-Supuestos!$B$2-Supuestos!$B$8),(F55+Supuestos!$B$3+Supuestos!$B$7)/(1-Supuestos!$B$2)),0)-0.01 | J55: 33.99 | K55: =J55-J55*Supuestos!$B$2-Supuestos!$B$3-F55 | L55: =K55/J55 | M55: =ROUNDUP(MAX(2*J55*0.92,(2*E55+Supuestos!$B$6+Supuestos!$B$3+8)/(1-Supuestos!$B$2)),0)-0.01 | N55: =M55-M55*Supuestos!$B$2-Supuestos!$B$3-2*E55-Supuestos!$B$6 | O55: Sin precio de mercado: precio objetivo | P55: Sin datos de mercado
A56: Frigidaire | B56: FRGPAAF1 | D56: 14.68 | E56: =D56*(1+Supuestos!$B$4) | F56: =E56+Supuestos!$B$5 | G56: =ROUNDUP((F56+Supuestos!$B$3+Supuestos!$B$9)/(1-Supuestos!$B$2),0)-0.01 | H56: =ROUNDUP(MAX((F56+Supuestos!$B$3)/(1-Supuestos!$B$2-Supuestos!$B$8),(F56+Supuestos!$B$3+Supuestos!$B$7)/(1-Supuestos!$B$2)),0)-0.01 | J56: 31.99 | K56: =J56-J56*Supuestos!$B$2-Supuestos!$B$3-F56 | L56: =K56/J56 | M56: =ROUNDUP(MAX(2*J56*0.92,(2*E56+Supuestos!$B$6+Supuestos!$B$3+8)/(1-Supuestos!$B$2)),0)-0.01 | N56: =M56-M56*Supuestos!$B$2-Supuestos!$B$3-2*E56-Supuestos!$B$6 | O56: Sin precio de mercado: precio objetivo | P56: Sin datos de mercado | R56: 6
A57: Frigidaire | B57: FRGPAAF2 | D57: 15.02 | E57: =D57*(1+Supuestos!$B$4) | F57: =E57+Supuestos!$B$5 | G57: =ROUNDUP((F57+Supuestos!$B$3+Supuestos!$B$9)/(1-Supuestos!$B$2),0)-0.01 | H57: =ROUNDUP(MAX((F57+Supuestos!$B$3)/(1-Supuestos!$B$2-Supuestos!$B$8),(F57+Supuestos!$B$3+Supuestos!$B$7)/(1-Supuestos!$B$2)),0)-0.01 | J57: 31.99 | K57: =J57-J57*Supuestos!$B$2-Supuestos!$B$3-F57 | L57: =K57/J57 | M57: =ROUNDUP(MAX(2*J57*0.92,(2*E57+Supuestos!$B$6+Supuestos!$B$3+8)/(1-Supuestos!$B$2)),0)-0.01 | N57: =M57-M57*Supuestos!$B$2-Supuestos!$B$3-2*E57-Supuestos!$B$6 | O57: Sin precio de mercado: precio objetivo | P57: Sin datos de mercado | R57: 6
A58: Frigidaire | B58: FRGPAAF12PK | D58: 29.35 | E58: =D58*(1+Supuestos!$B$4) | F58: =E58+Supuestos!$B$5 | G58: =ROUNDUP((F58+Supuestos!$B$3+Supuestos!$B$9)/(1-Supuestos!$B$2),0)-0.01 | H58: =ROUNDUP(MAX((F58+Supuestos!$B$3)/(1-Supuestos!$B$2-Supuestos!$B$8),(F58+Supuestos!$B$3+Supuestos!$B$7)/(1-Supuestos!$B$2)),0)-0.01 | J58: 49.99 | K58: =J58-J58*Supuestos!$B$2-Supuestos!$B$3-F58 | L58: =K58/J58 | M58: =ROUNDUP(MAX(2*J58*0.92,(2*E58+Supuestos!$B$6+Supuestos!$B$3+8)/(1-Supuestos!$B$2)),0)-0.01 | N58: =M58-M58*Supuestos!$B$2-Supuestos!$B$3-2*E58-Supuestos!$B$6 | O58: Sin precio de mercado: precio objetivo | P58: Sin datos de mercado
A59: Frigidaire | B59: FRGPAAF22PK | D59: 24.92 | E59: =D59*(1+Supuestos!$B$4) | F59: =E59+Supuestos!$B$5 | G59: =ROUNDUP((F59+Supuestos!$B$3+Supuestos!$B$9)/(1-Supuestos!$B$2),0)-0.01 | H59: =ROUNDUP(MAX((F59+Supuestos!$B$3)/(1-Supuestos!$B$2-Supuestos!$B$8),(F59+Supuestos!$B$3+Supuestos!$B$7)/(1-Supuestos!$B$2)),0)-0.01 | J59: 43.99 | K59: =J59-J59*Supuestos!$B$2-Supuestos!$B$3-F59 | L59: =K59/J59 | M59: =ROUNDUP(MAX(2*J59*0.92,(2*E59+Supuestos!$B$6+Supuestos!$B$3+8)/(1-Supuestos!$B$2)),0)-0.01 | N59: =M59-M59*Supuestos!$B$2-Supuestos!$B$3-2*E59-Supuestos!$B$6 | O59: Sin precio de mercado: precio objetivo | P59: Sin datos de mercado
A60: Frigidaire | B60: FRGPAAF24PK | D60: 44.3 | E60: =D60*(1+Supuestos!$B$4) | F60: =E60+Supuestos!$B$5 | G60: =ROUNDUP((F60+Supuestos!$B$3+Supuestos!$B$9)/(1-Supuestos!$B$2),0)-0.01 | H60: =ROUNDUP(MAX((F60+Supuestos!$B$3)/(1-Supuestos!$B$2-Supuestos!$B$8),(F60+Supuestos!$B$3+Supuestos!$B$7)/(1-Supuestos!$B$2)),0)-0.01 | J60: 69.99 | K60: =J60-J60*Supuestos!$B$2-Supuestos!$B$3-F60 | L60: =K60/J60 | M60: =ROUNDUP(MAX(2*J60*0.92,(2*E60+Supuestos!$B$6+Supuestos!$B$3+8)/(1-Supuestos!$B$2)),0)-0.01 | N60: =M60-M60*Supuestos!$B$2-Supuestos!$B$3-2*E60-Supuestos!$B$6 | O60: Sin precio de mercado: precio objetivo | P60: Sin datos de mercado
A61: Frigidaire | B61: FRPFUAF1 | D61: 9.59 | E61: =D61*(1+Supuestos!$B$4) | F61: =E61+Supuestos!$B$5 | G61: =ROUNDUP((F61+Supuestos!$B$3+Supuestos!$B$9)/(1-Supuestos!$B$2),0)-0.01 | H61: =ROUNDUP(MAX((F61+Supuestos!$B$3)/(1-Supuestos!$B$2-Supuestos!$B$8),(F61+Supuestos!$B$3+Supuestos!$B$7)/(1-Supuestos!$B$2)),0)-0.01 | J61: 25.99 | K61: =J61-J61*Supuestos!$B$2-Supuestos!$B$3-F61 | L61: =K61/J61 | M61: =ROUNDUP(MAX(2*J61*0.92,(2*E61+Supuestos!$B$6+Supuestos!$B$3+8)/(1-Supuestos!$B$2)),0)-0.01 | N61: =M61-M61*Supuestos!$B$2-Supuestos!$B$3-2*E61-Supuestos!$B$6 | O61: Sin precio de mercado: precio objetivo | P61: Sin datos de mercado | R61: 6
A62: Frigidaire | B62: FRPAPKRF | D62: 7.99 | E62: =D62*(1+Supuestos!$B$4) | F62: =E62+Supuestos!$B$5 | G62: =ROUNDUP((F62+Supuestos!$B$3+Supuestos!$B$9)/(1-Supuestos!$B$2),0)-0.01 | H62: =ROUNDUP(MAX((F62+Supuestos!$B$3)/(1-Supuestos!$B$2-Supuestos!$B$8),(F62+Supuestos!$B$3+Supuestos!$B$7)/(1-Supuestos!$B$2)),0)-0.01 | J62: 23.99 | K62: =J62-J62*Supuestos!$B$2-Supuestos!$B$3-F62 | L62: =K62/J62 | M62: =ROUNDUP(MAX(2*J62*0.92,(2*E62+Supuestos!$B$6+Supuestos!$B$3+8)/(1-Supuestos!$B$2)),0)-0.01 | N62: =M62-M62*Supuestos!$B$2-Supuestos!$B$3-2*E62-Supuestos!$B$6 | O62: Sin precio de mercado: precio objetivo | P62: Sin datos de mercado | R62: 6
A63: Frigidaire | B63: FRPAPK2RF | D63: 18.22 | E63: =D63*(1+Supuestos!$B$4) | F63: =E63+Supuestos!$B$5 | G63: =ROUNDUP((F63+Supuestos!$B$3+Supuestos!$B$9)/(1-Supuestos!$B$2),0)-0.01 | H63: =ROUNDUP(MAX((F63+Supuestos!$B$3)/(1-Supuestos!$B$2-Supuestos!$B$8),(F63+Supuestos!$B$3+Supuestos!$B$7)/(1-Supuestos!$B$2)),0)-0.01 | J63: 35.99 | K63: =J63-J63*Supuestos!$B$2-Supuestos!$B$3-F63 | L63: =K63/J63 | M63: =ROUNDUP(MAX(2*J63*0.92,(2*E63+Supuestos!$B$6+Supuestos!$B$3+8)/(1-Supuestos!$B$2)),0)-0.01 | N63: =M63-M63*Supuestos!$B$2-Supuestos!$B$3-2*E63-Supuestos!$B$6 | O63: Sin precio de mercado: precio objetivo | P63: Sin datos de mercado | R63: 6
A64: Whirlpool | B64: EDR1RXD1 | C64: wp-1-o | D64: 48 | E64: =D64*(1+Supuestos!$B$4) | F64: =E64+Supuestos!$B$5 | G64: =ROUNDUP((F64+Supuestos!$B$3+Supuestos!$B$9)/(1-Supuestos!$B$2),0)-0.01 | H64: =ROUNDUP(MAX((F64+Supuestos!$B$3)/(1-Supuestos!$B$2-Supuestos!$B$8),(F64+Supuestos!$B$3+Supuestos!$B$7)/(1-Supuestos!$B$2)),0)-0.01 | I64: 49.98 | O64: No vender suelto: el mercado está casi al precio de costo | P64: Amazon 49.98; lista 59.99; ofertas 30–33 | Q64: slickdeals.net, walmart.com | R64: 2
A65: Whirlpool | B65: EDR2RXD1 | C65: wp-2-o | D65: 48 | E65: =D65*(1+Supuestos!$B$4) | F65: =E65+Supuestos!$B$5 | G65: =ROUNDUP((F65+Supuestos!$B$3+Supuestos!$B$9)/(1-Supuestos!$B$2),0)-0.01 | H65: =ROUNDUP(MAX((F65+Supuestos!$B$3)/(1-Supuestos!$B$2-Supuestos!$B$8),(F65+Supuestos!$B$3+Supuestos!$B$7)/(1-Supuestos!$B$2)),0)-0.01 | I65: 49.49 | O65: No vender suelto: el mercado está casi al precio de costo | P65: Similar a EDR3/4/5 (49–57) | Q65: allfilters.com | R65: 2
A66: Whirlpool | B66: EDR3RXD1 | C66: wp-3-o | D66: 48 | E66: =D66*(1+Supuestos!$B$4) | F66: =E66+Supuestos!$B$5 | G66: =ROUNDUP((F66+Supuestos!$B$3+Supuestos!$B$9)/(1-Supuestos!$B$2),0)-0.01 | H66: =ROUNDUP(MAX((F66+Supuestos!$B$3)/(1-Supuestos!$B$2-Supuestos!$B$8),(F66+Supuestos!$B$3+Supuestos!$B$7)/(1-Supuestos!$B$2)),0)-0.01 | I66: 49.49 | O66: No vender suelto: el mercado está casi al precio de costo | P66: Allfilters 49.49; Walmart 48; Sears 56.57 | Q66: allfilters.com, walmart.com | R66: 2
A67: Whirlpool | B67: EDR4RXD1 | C67: wp-4-o | D67: 48 | E67: =D67*(1+Supuestos!$B$4) | F67: =E67+Supuestos!$B$5 | G67: =ROUNDUP((F67+Supuestos!$B$3+Supuestos!$B$9)/(1-Supuestos!$B$2),0)-0.01 | H67: =ROUNDUP(MAX((F67+Supuestos!$B$3)/(1-Supuestos!$B$2-Supuestos!$B$8),(F67+Supuestos!$B$3+Supuestos!$B$7)/(1-Supuestos!$B$2)),0)-0.01 | I67: 49.49 | O67: No vender suelto: el mercado está casi al precio de costo | P67: Allfilters 49.49; Walmart 50.80–52 | Q67: allfilters.com, walmart.com | R67: 2
A68: Whirlpool | B68: EDR5RXD1 | C68: wp-5-o | D68: 48 | E68: =D68*(1+Supuestos!$B$4) | F68: =E68+Supuestos!$B$5 | G68: =ROUNDUP((F68+Supuestos!$B$3+Supuestos!$B$9)/(1-Supuestos!$B$2),0)-0.01 | H68: =ROUNDUP(MAX((F68+Supuestos!$B$3)/(1-Supuestos!$B$2-Supuestos!$B$8),(F68+Supuestos!$B$3+Supuestos!$B$7)/(1-Supuestos!$B$2)),0)-0.01 | I68: 49.95 | O68: No vender suelto: el mercado está casi al precio de costo | P68: Allfilters 49.95; lista 59.99 | Q68: allfilters.com | R68: 2
A69: Whirlpool | B69: EDR6RXD1 | D69: 48 | E69: =D69*(1+Supuestos!$B$4) | F69: =E69+Supuestos!$B$5 | G69: =ROUNDUP((F69+Supuestos!$B$3+Supuestos!$B$9)/(1-Supuestos!$B$2),0)-0.01 | H69: =ROUNDUP(MAX((F69+Supuestos!$B$3)/(1-Supuestos!$B$2-Supuestos!$B$8),(F69+Supuestos!$B$3+Supuestos!$B$7)/(1-Supuestos!$B$2)),0)-0.01 | J69: 74.99 | K69: =J69-J69*Supuestos!$B$2-Supuestos!$B$3-F69 | L69: =K69/J69 | M69: =ROUNDUP(MAX(2*J69*0.92,(2*E69+Supuestos!$B$6+Supuestos!$B$3+8)/(1-Supuestos!$B$2)),0)-0.01 | N69: =M69-M69*Supuestos!$B$2-Supuestos!$B$3-2*E69-Supuestos!$B$6 | O69: Sin precio de mercado: precio objetivo | P69: Sin datos de mercado | R69: 2
A70: Whirlpool | B70: EDRARXD1 | D70: 48 | E70: =D70*(1+Supuestos!$B$4) | F70: =E70+Supuestos!$B$5 | G70: =ROUNDUP((F70+Supuestos!$B$3+Supuestos!$B$9)/(1-Supuestos!$B$2),0)-0.01 | H70: =ROUNDUP(MAX((F70+Supuestos!$B$3)/(1-Supuestos!$B$2-Supuestos!$B$8),(F70+Supuestos!$B$3+Supuestos!$B$7)/(1-Supuestos!$B$2)),0)-0.01 | J70: 74.99 | K70: =J70-J70*Supuestos!$B$2-Supuestos!$B$3-F70 | L70: =K70/J70 | M70: =ROUNDUP(MAX(2*J70*0.92,(2*E70+Supuestos!$B$6+Supuestos!$B$3+8)/(1-Supuestos!$B$2)),0)-0.01 | N70: =M70-M70*Supuestos!$B$2-Supuestos!$B$3-2*E70-Supuestos!$B$6 | O70: Sin precio de mercado: precio objetivo | P70: Sin datos de mercado | R70: 2
A71: Whirlpool | B71: 4378411RB | C71: wp-ex-o | D71: 9.4 | E71: =D71*(1+Supuestos!$B$4) | F71: =E71+Supuestos!$B$5 | G71: =ROUNDUP((F71+Supuestos!$B$3+Supuestos!$B$9)/(1-Supuestos!$B$2),0)-0.01 | H71: =ROUNDUP(MAX((F71+Supuestos!$B$3)/(1-Supuestos!$B$2-Supuestos!$B$8),(F71+Supuestos!$B$3+Supuestos!$B$7)/(1-Supuestos!$B$2)),0)-0.01 | I71: 23.49 | J71: 25.99 | K71: =J71-J71*Supuestos!$B$2-Supuestos!$B$3-F71 | L71: =K71/J71 | M71: =ROUNDUP(MAX(2*J71*0.92,(2*E71+Supuestos!$B$6+Supuestos!$B$3+8)/(1-Supuestos!$B$2)),0)-0.01 | N71: =M71-M71*Supuestos!$B$2-Supuestos!$B$3-2*E71-Supuestos!$B$6 | O71: Competitivo | P71: Slyman Bros 23.49 | Q71: slymanbros.com | R71: 30
A72: Whirlpool | B72: F2WC9I1 | D72: 42 | E72: =D72*(1+Supuestos!$B$4) | F72: =E72+Supuestos!$B$5 | G72: =ROUNDUP((F72+Supuestos!$B$3+Supuestos!$B$9)/(1-Supuestos!$B$2),0)-0.01 | H72: =ROUNDUP(MAX((F72+Supuestos!$B$3)/(1-Supuestos!$B$2-Supuestos!$B$8),(F72+Supuestos!$B$3+Supuestos!$B$7)/(1-Supuestos!$B$2)),0)-0.01 | J72: 66.99 | K72: =J72-J72*Supuestos!$B$2-Supuestos!$B$3-F72 | L72: =K72/J72 | M72: =ROUNDUP(MAX(2*J72*0.92,(2*E72+Supuestos!$B$6+Supuestos!$B$3+8)/(1-Supuestos!$B$2)),0)-0.01 | N72: =M72-M72*Supuestos!$B$2-Supuestos!$B$3-2*E72-Supuestos!$B$6 | O72: Sin precio de mercado: precio objetivo | P72: Sin datos de mercado | R72: 2
A73: Whirlpool | B73: W10311524 | D73: 7.75 | E73: =D73*(1+Supuestos!$B$4) | F73: =E73+Supuestos!$B$5 | G73: =ROUNDUP((F73+Supuestos!$B$3+Supuestos!$B$9)/(1-Supuestos!$B$2),0)-0.01 | H73: =ROUNDUP(MAX((F73+Supuestos!$B$3)/(1-Supuestos!$B$2-Supuestos!$B$8),(F73+Supuestos!$B$3+Supuestos!$B$7)/(1-Supuestos!$B$2)),0)-0.01 | J73: 23.99 | K73: =J73-J73*Supuestos!$B$2-Supuestos!$B$3-F73 | L73: =K73/J73 | M73: =ROUNDUP(MAX(2*J73*0.92,(2*E73+Supuestos!$B$6+Supuestos!$B$3+8)/(1-Supuestos!$B$2)),0)-0.01 | N73: =M73-M73*Supuestos!$B$2-Supuestos!$B$3-2*E73-Supuestos!$B$6 | O73: Sin precio de mercado: precio objetivo | P73: Sin datos de mercado
A74: Kenmore | B74: 9490.0 | D74: 24.5 | E74: =D74*(1+Supuestos!$B$4) | F74: =E74+Supuestos!$B$5 | G74: =ROUNDUP((F74+Supuestos!$B$3+Supuestos!$B$9)/(1-Supuestos!$B$2),0)-0.01 | H74: =ROUNDUP(MAX((F74+Supuestos!$B$3)/(1-Supuestos!$B$2-Supuestos!$B$8),(F74+Supuestos!$B$3+Supuestos!$B$7)/(1-Supuestos!$B$2)),0)-0.01 | J74: 43.99 | K74: =J74-J74*Supuestos!$B$2-Supuestos!$B$3-F74 | L74: =K74/J74 | M74: =ROUNDUP(MAX(2*J74*0.92,(2*E74+Supuestos!$B$6+Supuestos!$B$3+8)/(1-Supuestos!$B$2)),0)-0.01 | N74: =M74-M74*Supuestos!$B$2-Supuestos!$B$3-2*E74-Supuestos!$B$6 | O74: Sin precio de mercado: precio objetivo | P74: Sin datos de mercado | R74: 49
A75: Kenmore | B75: 9690.0 | D75: 24.5 | E75: =D75*(1+Supuestos!$B$4) | F75: =E75+Supuestos!$B$5 | G75: =ROUNDUP((F75+Supuestos!$B$3+Supuestos!$B$9)/(1-Supuestos!$B$2),0)-0.01 | H75: =ROUNDUP(MAX((F75+Supuestos!$B$3)/(1-Supuestos!$B$2-Supuestos!$B$8),(F75+Supuestos!$B$3+Supuestos!$B$7)/(1-Supuestos!$B$2)),0)-0.01 | J75: 43.99 | K75: =J75-J75*Supuestos!$B$2-Supuestos!$B$3-F75 | L75: =K75/J75 | M75: =ROUNDUP(MAX(2*J75*0.92,(2*E75+Supuestos!$B$6+Supuestos!$B$3+8)/(1-Supuestos!$B$2)),0)-0.01 | N75: =M75-M75*Supuestos!$B$2-Supuestos!$B$3-2*E75-Supuestos!$B$6 | O75: Sin precio de mercado: precio objetivo | P75: Sin datos de mercado | R75: 36
A76: Kenmore | B76: 9890.0 | D76: 24.5 | E76: =D76*(1+Supuestos!$B$4) | F76: =E76+Supuestos!$B$5 | G76: =ROUNDUP((F76+Supuestos!$B$3+Supuestos!$B$9)/(1-Supuestos!$B$2),0)-0.01 | H76: =ROUNDUP(MAX((F76+Supuestos!$B$3)/(1-Supuestos!$B$2-Supuestos!$B$8),(F76+Supuestos!$B$3+Supuestos!$B$7)/(1-Supuestos!$B$2)),0)-0.01 | J76: 43.99 | K76: =J76-J76*Supuestos!$B$2-Supuestos!$B$3-F76 | L76: =K76/J76 | M76: =ROUNDUP(MAX(2*J76*0.92,(2*E76+Supuestos!$B$6+Supuestos!$B$3+8)/(1-Supuestos!$B$2)),0)-0.01 | N76: =M76-M76*Supuestos!$B$2-Supuestos!$B$3-2*E76-Supuestos!$B$6 | O76: Sin precio de mercado: precio objetivo | P76: Sin datos de mercado | R76: 36
A77: Kenmore | B77: 9980.0 | D77: 24.5 | E77: =D77*(1+Supuestos!$B$4) | F77: =E77+Supuestos!$B$5 | G77: =ROUNDUP((F77+Supuestos!$B$3+Supuestos!$B$9)/(1-Supuestos!$B$2),0)-0.01 | H77: =ROUNDUP(MAX((F77+Supuestos!$B$3)/(1-Supuestos!$B$2-Supuestos!$B$8),(F77+Supuestos!$B$3+Supuestos!$B$7)/(1-Supuestos!$B$2)),0)-0.01 | J77: 43.99 | K77: =J77-J77*Supuestos!$B$2-Supuestos!$B$3-F77 | L77: =K77/J77 | M77: =ROUNDUP(MAX(2*J77*0.92,(2*E77+Supuestos!$B$6+Supuestos!$B$3+8)/(1-Supuestos!$B$2)),0)-0.01 | N77: =M77-M77*Supuestos!$B$2-Supuestos!$B$3-2*E77-Supuestos!$B$6 | O77: Sin precio de mercado: precio objetivo | P77: Sin datos de mercado | R77: 36
A78: Kenmore | B78: 9990.0 | D78: 24.5 | E78: =D78*(1+Supuestos!$B$4) | F78: =E78+Supuestos!$B$5 | G78: =ROUNDUP((F78+Supuestos!$B$3+Supuestos!$B$9)/(1-Supuestos!$B$2),0)-0.01 | H78: =ROUNDUP(MAX((F78+Supuestos!$B$3)/(1-Supuestos!$B$2-Supuestos!$B$8),(F78+Supuestos!$B$3+Supuestos!$B$7)/(1-Supuestos!$B$2)),0)-0.01 | J78: 43.99 | K78: =J78-J78*Supuestos!$B$2-Supuestos!$B$3-F78 | L78: =K78/J78 | M78: =ROUNDUP(MAX(2*J78*0.92,(2*E78+Supuestos!$B$6+Supuestos!$B$3+8)/(1-Supuestos!$B$2)),0)-0.01 | N78: =M78-M78*Supuestos!$B$2-Supuestos!$B$3-2*E78-Supuestos!$B$6 | O78: Sin precio de mercado: precio objetivo | P78: Sin datos de mercado | R78: 24
A79: Electrolux | B79: 5304492441.0 | D79: 19.5 | E79: =D79*(1+Supuestos!$B$4) | F79: =E79+Supuestos!$B$5 | G79: =ROUNDUP((F79+Supuestos!$B$3+Supuestos!$B$9)/(1-Supuestos!$B$2),0)-0.01 | H79: =ROUNDUP(MAX((F79+Supuestos!$B$3)/(1-Supuestos!$B$2-Supuestos!$B$8),(F79+Supuestos!$B$3+Supuestos!$B$7)/(1-Supuestos!$B$2)),0)-0.01 | J79: 36.99 | K79: =J79-J79*Supuestos!$B$2-Supuestos!$B$3-F79 | L79: =K79/J79 | M79: =ROUNDUP(MAX(2*J79*0.92,(2*E79+Supuestos!$B$6+Supuestos!$B$3+8)/(1-Supuestos!$B$2)),0)-0.01 | N79: =M79-M79*Supuestos!$B$2-Supuestos!$B$3-2*E79-Supuestos!$B$6 | O79: Sin precio de mercado: precio objetivo | P79: Sin datos de mercado | R79: 4
A80: Electrolux | B80: EAFCBF | D80: 15.59 | E80: =D80*(1+Supuestos!$B$4) | F80: =E80+Supuestos!$B$5 | G80: =ROUNDUP((F80+Supuestos!$B$3+Supuestos!$B$9)/(1-Supuestos!$B$2),0)-0.01 | H80: =ROUNDUP(MAX((F80+Supuestos!$B$3)/(1-Supuestos!$B$2-Supuestos!$B$8),(F80+Supuestos!$B$3+Supuestos!$B$7)/(1-Supuestos!$B$2)),0)-0.01 | J80: 32.99 | K80: =J80-J80*Supuestos!$B$2-Supuestos!$B$3-F80 | L80: =K80/J80 | M80: =ROUNDUP(MAX(2*J80*0.92,(2*E80+Supuestos!$B$6+Supuestos!$B$3+8)/(1-Supuestos!$B$2)),0)-0.01 | N80: =M80-M80*Supuestos!$B$2-Supuestos!$B$3-2*E80-Supuestos!$B$6 | O80: Sin precio de mercado: precio objetivo | P80: Sin datos de mercado | R80: 12
A81: Electrolux | B81: EAF1CB | D81: 12.98 | E81: =D81*(1+Supuestos!$B$4) | F81: =E81+Supuestos!$B$5 | G81: =ROUNDUP((F81+Supuestos!$B$3+Supuestos!$B$9)/(1-Supuestos!$B$2),0)-0.01 | H81: =ROUNDUP(MAX((F81+Supuestos!$B$3)/(1-Supuestos!$B$2-Supuestos!$B$8),(F81+Supuestos!$B$3+Supuestos!$B$7)/(1-Supuestos!$B$2)),0)-0.01 | J81: 29.99 | K81: =J81-J81*Supuestos!$B$2-Supuestos!$B$3-F81 | L81: =K81/J81 | M81: =ROUNDUP(MAX(2*J81*0.92,(2*E81+Supuestos!$B$6+Supuestos!$B$3+8)/(1-Supuestos!$B$2)),0)-0.01 | N81: =M81-M81*Supuestos!$B$2-Supuestos!$B$3-2*E81-Supuestos!$B$6 | O81: Sin precio de mercado: precio objetivo | P81: Sin datos de mercado | R81: 12
A82: Electrolux | B82: EPPWFU01 | D82: 49 | E82: =D82*(1+Supuestos!$B$4) | F82: =E82+Supuestos!$B$5 | G82: =ROUNDUP((F82+Supuestos!$B$3+Supuestos!$B$9)/(1-Supuestos!$B$2),0)-0.01 | H82: =ROUNDUP(MAX((F82+Supuestos!$B$3)/(1-Supuestos!$B$2-Supuestos!$B$8),(F82+Supuestos!$B$3+Supuestos!$B$7)/(1-Supuestos!$B$2)),0)-0.01 | J82: 76.99 | K82: =J82-J82*Supuestos!$B$2-Supuestos!$B$3-F82 | L82: =K82/J82 | M82: =ROUNDUP(MAX(2*J82*0.92,(2*E82+Supuestos!$B$6+Supuestos!$B$3+8)/(1-Supuestos!$B$2)),0)-0.01 | N82: =M82-M82*Supuestos!$B$2-Supuestos!$B$3-2*E82-Supuestos!$B$6 | O82: Sin precio de mercado: precio objetivo | P82: Sin datos de mercado | R82: 6
A83: Electrolux | B83: EWF01 | D83: 33 | E83: =D83*(1+Supuestos!$B$4) | F83: =E83+Supuestos!$B$5 | G83: =ROUNDUP((F83+Supuestos!$B$3+Supuestos!$B$9)/(1-Supuestos!$B$2),0)-0.01 | H83: =ROUNDUP(MAX((F83+Supuestos!$B$3)/(1-Supuestos!$B$2-Supuestos!$B$8),(F83+Supuestos!$B$3+Supuestos!$B$7)/(1-Supuestos!$B$2)),0)-0.01 | J83: 54.99 | K83: =J83-J83*Supuestos!$B$2-Supuestos!$B$3-F83 | L83: =K83/J83 | M83: =ROUNDUP(MAX(2*J83*0.92,(2*E83+Supuestos!$B$6+Supuestos!$B$3+8)/(1-Supuestos!$B$2)),0)-0.01 | N83: =M83-M83*Supuestos!$B$2-Supuestos!$B$3-2*E83-Supuestos!$B$6 | O83: Sin precio de mercado: precio objetivo | P83: Sin datos de mercado | R83: 6
A84: Electrolux | B84: EWF02 | D84: 43.2 | E84: =D84*(1+Supuestos!$B$4) | F84: =E84+Supuestos!$B$5 | G84: =ROUNDUP((F84+Supuestos!$B$3+Supuestos!$B$9)/(1-Supuestos!$B$2),0)-0.01 | H84: =ROUNDUP(MAX((F84+Supuestos!$B$3)/(1-Supuestos!$B$2-Supuestos!$B$8),(F84+Supuestos!$B$3+Supuestos!$B$7)/(1-Supuestos!$B$2)),0)-0.01 | J84: 68.99 | K84: =J84-J84*Supuestos!$B$2-Supuestos!$B$3-F84 | L84: =K84/J84 | M84: =ROUNDUP(MAX(2*J84*0.92,(2*E84+Supuestos!$B$6+Supuestos!$B$3+8)/(1-Supuestos!$B$2)),0)-0.01 | N84: =M84-M84*Supuestos!$B$2-Supuestos!$B$3-2*E84-Supuestos!$B$6 | O84: Sin precio de mercado: precio objetivo | P84: Sin datos de mercado | R84: 2
A85: Electrolux | B85: EWF2CBPA | D85: 36 | E85: =D85*(1+Supuestos!$B$4) | F85: =E85+Supuestos!$B$5 | G85: =ROUNDUP((F85+Supuestos!$B$3+Supuestos!$B$9)/(1-Supuestos!$B$2),0)-0.01 | H85: =ROUNDUP(MAX((F85+Supuestos!$B$3)/(1-Supuestos!$B$2-Supuestos!$B$8),(F85+Supuestos!$B$3+Supuestos!$B$7)/(1-Supuestos!$B$2)),0)-0.01 | J85: 58.99 | K85: =J85-J85*Supuestos!$B$2-Supuestos!$B$3-F85 | L85: =K85/J85 | M85: =ROUNDUP(MAX(2*J85*0.92,(2*E85+Supuestos!$B$6+Supuestos!$B$3+8)/(1-Supuestos!$B$2)),0)-0.01 | N85: =M85-M85*Supuestos!$B$2-Supuestos!$B$3-2*E85-Supuestos!$B$6 | O85: Sin precio de mercado: precio objetivo | P85: Sin datos de mercado | R85: 6
A86: Electrolux | B86: SCWF3CTO | D86: 22.2 | E86: =D86*(1+Supuestos!$B$4) | F86: =E86+Supuestos!$B$5 | G86: =ROUNDUP((F86+Supuestos!$B$3+Supuestos!$B$9)/(1-Supuestos!$B$2),0)-0.01 | H86: =ROUNDUP(MAX((F86+Supuestos!$B$3)/(1-Supuestos!$B$2-Supuestos!$B$8),(F86+Supuestos!$B$3+Supuestos!$B$7)/(1-Supuestos!$B$2)),0)-0.01 | J86: 39.99 | K86: =J86-J86*Supuestos!$B$2-Supuestos!$B$3-F86 | L86: =K86/J86 | M86: =ROUNDUP(MAX(2*J86*0.92,(2*E86+Supuestos!$B$6+Supuestos!$B$3+8)/(1-Supuestos!$B$2)),0)-0.01 | N86: =M86-M86*Supuestos!$B$2-Supuestos!$B$3-2*E86-Supuestos!$B$6 | O86: Sin precio de mercado: precio objetivo | P86: Sin datos de mercado | R86: 6
A87: Bosch | B87: BORPLFTR55 / 11032531 | D87: 36.5 | E87: =D87*(1+Supuestos!$B$4) | F87: =E87+Supuestos!$B$5 | G87: =ROUNDUP((F87+Supuestos!$B$3+Supuestos!$B$9)/(1-Supuestos!$B$2),0)-0.01 | H87: =ROUNDUP(MAX((F87+Supuestos!$B$3)/(1-Supuestos!$B$2-Supuestos!$B$8),(F87+Supuestos!$B$3+Supuestos!$B$7)/(1-Supuestos!$B$2)),0)-0.01 | J87: 59.99 | K87: =J87-J87*Supuestos!$B$2-Supuestos!$B$3-F87 | L87: =K87/J87 | M87: =ROUNDUP(MAX(2*J87*0.92,(2*E87+Supuestos!$B$6+Supuestos!$B$3+8)/(1-Supuestos!$B$2)),0)-0.01 | N87: =M87-M87*Supuestos!$B$2-Supuestos!$B$3-2*E87-Supuestos!$B$6 | O87: Sin precio de mercado: precio objetivo | P87: Sin datos de mercado | R87: 54 | S87: *Compatible with: Gaggenau - Model # RA450022, Part # 11032531 Thermador - Model # REPLFLTR55, Part # 11032531
A88: Bosch | B88: BORPLFTR30 / 11034152 | D88: 36.5 | E88: =D88*(1+Supuestos!$B$4) | F88: =E88+Supuestos!$B$5 | G88: =ROUNDUP((F88+Supuestos!$B$3+Supuestos!$B$9)/(1-Supuestos!$B$2),0)-0.01 | H88: =ROUNDUP(MAX((F88+Supuestos!$B$3)/(1-Supuestos!$B$2-Supuestos!$B$8),(F88+Supuestos!$B$3+Supuestos!$B$7)/(1-Supuestos!$B$2)),0)-0.01 | J88: 59.99 | K88: =J88-J88*Supuestos!$B$2-Supuestos!$B$3-F88 | L88: =K88/J88 | M88: =ROUNDUP(MAX(2*J88*0.92,(2*E88+Supuestos!$B$6+Supuestos!$B$3+8)/(1-Supuestos!$B$2)),0)-0.01 | N88: =M88-M88*Supuestos!$B$2-Supuestos!$B$3-2*E88-Supuestos!$B$6 | O88: Sin precio de mercado: precio objetivo | P88: Sin datos de mercado | R88: 54 | S88: *Compatible with: Gaggenau - Model # RA450021, Part #11034152 Thermador - Model # REPLFLTR30, Part # 11034152
A89: LIEBHERR | B89: 744000200.0 | D89: 83 | E89: =D89*(1+Supuestos!$B$4) | F89: =E89+Supuestos!$B$5 | G89: =ROUNDUP((F89+Supuestos!$B$3+Supuestos!$B$9)/(1-Supuestos!$B$2),0)-0.01 | H89: =ROUNDUP(MAX((F89+Supuestos!$B$3)/(1-Supuestos!$B$2-Supuestos!$B$8),(F89+Supuestos!$B$3+Supuestos!$B$7)/(1-Supuestos!$B$2)),0)-0.01 | J89: 122.99 | K89: =J89-J89*Supuestos!$B$2-Supuestos!$B$3-F89 | L89: =K89/J89 | M89: =ROUNDUP(MAX(2*J89*0.92,(2*E89+Supuestos!$B$6+Supuestos!$B$3+8)/(1-Supuestos!$B$2)),0)-0.01 | N89: =M89-M89*Supuestos!$B$2-Supuestos!$B$3-2*E89-Supuestos!$B$6 | O89: Sin precio de mercado: precio objetivo | P89: Sin datos de mercado | R89: 24
A90: OMNIFILTER | B90: R200 | D90: 18.25 | E90: =D90*(1+Supuestos!$B$4) | F90: =E90+Supuestos!$B$5 | G90: =ROUNDUP((F90+Supuestos!$B$3+Supuestos!$B$9)/(1-Supuestos!$B$2),0)-0.01 | H90: =ROUNDUP(MAX((F90+Supuestos!$B$3)/(1-Supuestos!$B$2-Supuestos!$B$8),(F90+Supuestos!$B$3+Supuestos!$B$7)/(1-Supuestos!$B$2)),0)-0.01 | J90: 35.99 | K90: =J90-J90*Supuestos!$B$2-Supuestos!$B$3-F90 | L90: =K90/J90 | M90: =ROUNDUP(MAX(2*J90*0.92,(2*E90+Supuestos!$B$6+Supuestos!$B$3+8)/(1-Supuestos!$B$2)),0)-0.01 | N90: =M90-M90*Supuestos!$B$2-Supuestos!$B$3-2*E90-Supuestos!$B$6 | O90: Sin precio de mercado: precio objetivo | P90: Sin datos de mercado | R90: 6
A91: Culligan | B91: IC-EZ-3 | D91: 60 | E91: =D91*(1+Supuestos!$B$4) | F91: =E91+Supuestos!$B$5 | G91: =ROUNDUP((F91+Supuestos!$B$3+Supuestos!$B$9)/(1-Supuestos!$B$2),0)-0.01 | H91: =ROUNDUP(MAX((F91+Supuestos!$B$3)/(1-Supuestos!$B$2-Supuestos!$B$8),(F91+Supuestos!$B$3+Supuestos!$B$7)/(1-Supuestos!$B$2)),0)-0.01 | J91: 91.99 | K91: =J91-J91*Supuestos!$B$2-Supuestos!$B$3-F91 | L91: =K91/J91 | M91: =ROUNDUP(MAX(2*J91*0.92,(2*E91+Supuestos!$B$6+Supuestos!$B$3+8)/(1-Supuestos!$B$2)),0)-0.01 | N91: =M91-M91*Supuestos!$B$2-Supuestos!$B$3-2*E91-Supuestos!$B$6 | O91: Sin precio de mercado: precio objetivo | P91: Sin datos de mercado | R91: 6
A92: Culligan | B92: IC-EZ-1 | D92: 32 | E92: =D92*(1+Supuestos!$B$4) | F92: =E92+Supuestos!$B$5 | G92: =ROUNDUP((F92+Supuestos!$B$3+Supuestos!$B$9)/(1-Supuestos!$B$2),0)-0.01 | H92: =ROUNDUP(MAX((F92+Supuestos!$B$3)/(1-Supuestos!$B$2-Supuestos!$B$8),(F92+Supuestos!$B$3+Supuestos!$B$7)/(1-Supuestos!$B$2)),0)-0.01 | J92: 53.99 | K92: =J92-J92*Supuestos!$B$2-Supuestos!$B$3-F92 | L92: =K92/J92 | M92: =ROUNDUP(MAX(2*J92*0.92,(2*E92+Supuestos!$B$6+Supuestos!$B$3+8)/(1-Supuestos!$B$2)),0)-0.01 | N92: =M92-M92*Supuestos!$B$2-Supuestos!$B$3-2*E92-Supuestos!$B$6 | O92: Sin precio de mercado: precio objetivo | P92: Sin datos de mercado | R92: 6
A93: Everpure | B93: Everpure H300 Cartridge EV927072 | D93: 102 | E93: =D93*(1+Supuestos!$B$4) | F93: =E93+Supuestos!$B$5 | G93: =ROUNDUP((F93+Supuestos!$B$3+Supuestos!$B$9)/(1-Supuestos!$B$2),0)-0.01 | H93: =ROUNDUP(MAX((F93+Supuestos!$B$3)/(1-Supuestos!$B$2-Supuestos!$B$8),(F93+Supuestos!$B$3+Supuestos!$B$7)/(1-Supuestos!$B$2)),0)-0.01 | J93: 148.99 | K93: =J93-J93*Supuestos!$B$2-Supuestos!$B$3-F93 | L93: =K93/J93 | M93: =ROUNDUP(MAX(2*J93*0.92,(2*E93+Supuestos!$B$6+Supuestos!$B$3+8)/(1-Supuestos!$B$2)),0)-0.01 | N93: =M93-M93*Supuestos!$B$2-Supuestos!$B$3-2*E93-Supuestos!$B$6 | O93: Sin precio de mercado: precio objetivo | P93: Sin datos de mercado | R93: 6
A94: Everpure | B94: Everpure H300 System EV927076 | D94: 260 | E94: =D94*(1+Supuestos!$B$4) | F94: =E94+Supuestos!$B$5 | G94: =ROUNDUP((F94+Supuestos!$B$3+Supuestos!$B$9)/(1-Supuestos!$B$2),0)-0.01 | H94: =ROUNDUP(MAX((F94+Supuestos!$B$3)/(1-Supuestos!$B$2-Supuestos!$B$8),(F94+Supuestos!$B$3+Supuestos!$B$7)/(1-Supuestos!$B$2)),0)-0.01 | J94: 362.99 | K94: =J94-J94*Supuestos!$B$2-Supuestos!$B$3-F94 | L94: =K94/J94 | M94: =ROUNDUP(MAX(2*J94*0.92,(2*E94+Supuestos!$B$6+Supuestos!$B$3+8)/(1-Supuestos!$B$2)),0)-0.01 | N94: =M94-M94*Supuestos!$B$2-Supuestos!$B$3-2*E94-Supuestos!$B$6 | O94: Sin precio de mercado: precio objetivo | P94: Sin datos de mercado | R94: 1
A95: Everpure | B95: Everpure H300 NXT Cartridge EV927441 | D95: 103 | E95: =D95*(1+Supuestos!$B$4) | F95: =E95+Supuestos!$B$5 | G95: =ROUNDUP((F95+Supuestos!$B$3+Supuestos!$B$9)/(1-Supuestos!$B$2),0)-0.01 | H95: =ROUNDUP(MAX((F95+Supuestos!$B$3)/(1-Supuestos!$B$2-Supuestos!$B$8),(F95+Supuestos!$B$3+Supuestos!$B$7)/(1-Supuestos!$B$2)),0)-0.01 | J95: 149.99 | K95: =J95-J95*Supuestos!$B$2-Supuestos!$B$3-F95 | L95: =K95/J95 | M95: =ROUNDUP(MAX(2*J95*0.92,(2*E95+Supuestos!$B$6+Supuestos!$B$3+8)/(1-Supuestos!$B$2)),0)-0.01 | N95: =M95-M95*Supuestos!$B$2-Supuestos!$B$3-2*E95-Supuestos!$B$6 | O95: Sin precio de mercado: precio objetivo | P95: Sin datos de mercado | R95: 6
A96: Everpure | B96: Everpure H300 HSD Cartridge EV927075 | D96: 103 | E96: =D96*(1+Supuestos!$B$4) | F96: =E96+Supuestos!$B$5 | G96: =ROUNDUP((F96+Supuestos!$B$3+Supuestos!$B$9)/(1-Supuestos!$B$2),0)-0.01 | H96: =ROUNDUP(MAX((F96+Supuestos!$B$3)/(1-Supuestos!$B$2-Supuestos!$B$8),(F96+Supuestos!$B$3+Supuestos!$B$7)/(1-Supuestos!$B$2)),0)-0.01 | J96: 149.99 | K96: =J96-J96*Supuestos!$B$2-Supuestos!$B$3-F96 | L96: =K96/J96 | M96: =ROUNDUP(MAX(2*J96*0.92,(2*E96+Supuestos!$B$6+Supuestos!$B$3+8)/(1-Supuestos!$B$2)),0)-0.01 | N96: =M96-M96*Supuestos!$B$2-Supuestos!$B$3-2*E96-Supuestos!$B$6 | O96: Sin precio de mercado: precio objetivo | P96: Sin datos de mercado | R96: 6
A97: Everpure | B97: Everpure H1200 System EV928200 | D97: 360 | E97: =D97*(1+Supuestos!$B$4) | F97: =E97+Supuestos!$B$5 | G97: =ROUNDUP((F97+Supuestos!$B$3+Supuestos!$B$9)/(1-Supuestos!$B$2),0)-0.01 | H97: =ROUNDUP(MAX((F97+Supuestos!$B$3)/(1-Supuestos!$B$2-Supuestos!$B$8),(F97+Supuestos!$B$3+Supuestos!$B$7)/(1-Supuestos!$B$2)),0)-0.01 | J97: 498.99 | K97: =J97-J97*Supuestos!$B$2-Supuestos!$B$3-F97 | L97: =K97/J97 | M97: =ROUNDUP(MAX(2*J97*0.92,(2*E97+Supuestos!$B$6+Supuestos!$B$3+8)/(1-Supuestos!$B$2)),0)-0.01 | N97: =M97-M97*Supuestos!$B$2-Supuestos!$B$3-2*E97-Supuestos!$B$6 | O97: Sin precio de mercado: precio objetivo | P97: Sin datos de mercado | R97: 1
A98: Everpure | B98: Everpure H1200 Cartridge kit EV928201 | D98: 186 | E98: =D98*(1+Supuestos!$B$4) | F98: =E98+Supuestos!$B$5 | G98: =ROUNDUP((F98+Supuestos!$B$3+Supuestos!$B$9)/(1-Supuestos!$B$2),0)-0.01 | H98: =ROUNDUP(MAX((F98+Supuestos!$B$3)/(1-Supuestos!$B$2-Supuestos!$B$8),(F98+Supuestos!$B$3+Supuestos!$B$7)/(1-Supuestos!$B$2)),0)-0.01 | J98: 262.99 | K98: =J98-J98*Supuestos!$B$2-Supuestos!$B$3-F98 | L98: =K98/J98 | M98: =ROUNDUP(MAX(2*J98*0.92,(2*E98+Supuestos!$B$6+Supuestos!$B$3+8)/(1-Supuestos!$B$2)),0)-0.01 | N98: =M98-M98*Supuestos!$B$2-Supuestos!$B$3-2*E98-Supuestos!$B$6 | O98: Sin precio de mercado: precio objetivo | P98: Sin datos de mercado | R98: 6
A99: Everpure | B99: Everpure H104 Cartridge EV961211 | D99: 72 | E99: =D99*(1+Supuestos!$B$4) | F99: =E99+Supuestos!$B$5 | G99: =ROUNDUP((F99+Supuestos!$B$3+Supuestos!$B$9)/(1-Supuestos!$B$2),0)-0.01 | H99: =ROUNDUP(MAX((F99+Supuestos!$B$3)/(1-Supuestos!$B$2-Supuestos!$B$8),(F99+Supuestos!$B$3+Supuestos!$B$7)/(1-Supuestos!$B$2)),0)-0.01 | J99: 107.99 | K99: =J99-J99*Supuestos!$B$2-Supuestos!$B$3-F99 | L99: =K99/J99 | M99: =ROUNDUP(MAX(2*J99*0.92,(2*E99+Supuestos!$B$6+Supuestos!$B$3+8)/(1-Supuestos!$B$2)),0)-0.01 | N99: =M99-M99*Supuestos!$B$2-Supuestos!$B$3-2*E99-Supuestos!$B$6 | O99: Sin precio de mercado: precio objetivo | P99: Sin datos de mercado | R99: 6
A100: Everpure | B100: Everpure H104 System EV926271 | D100: 201 | E100: =D100*(1+Supuestos!$B$4) | F100: =E100+Supuestos!$B$5 | G100: =ROUNDUP((F100+Supuestos!$B$3+Supuestos!$B$9)/(1-Supuestos!$B$2),0)-0.01 | H100: =ROUNDUP(MAX((F100+Supuestos!$B$3)/(1-Supuestos!$B$2-Supuestos!$B$8),(F100+Supuestos!$B$3+Supuestos!$B$7)/(1-Supuestos!$B$2)),0)-0.01 | J100: 282.99 | K100: =J100-J100*Supuestos!$B$2-Supuestos!$B$3-F100 | L100: =K100/J100 | M100: =ROUNDUP(MAX(2*J100*0.92,(2*E100+Supuestos!$B$6+Supuestos!$B$3+8)/(1-Supuestos!$B$2)),0)-0.01 | N100: =M100-M100*Supuestos!$B$2-Supuestos!$B$3-2*E100-Supuestos!$B$6 | O100: Sin precio de mercado: precio objetivo | P100: Sin datos de mercado | R100: 1
... A105: Midea | B105: MIWF8200 | D105: 39 | E105: =D105*(1+Supuestos!$B$4) | F105: =E105+Supuestos!$B$5 | G105: =ROUNDUP((F105+Supuestos!$B$3+Supuestos!$B$9)/(1-Supuestos!$B$2),0)-0.01 | H105: =ROUNDUP(MAX((F105+Supuestos!$B$3)/(1-Supuestos!$B$2-Supuestos!$B$8),(F105+Supuestos!$B$3+Supuestos!$B$7)/(1-Supuestos!$B$2)),0)-0.01 | J105: 62.99 | K105: =J105-J105*Supuestos!$B$2-Supuestos!$B$3-F105 | L105: =K105/J105 | M105: =ROUNDUP(MAX(2*J105*0.92,(2*E105+Supuestos!$B$6+Supuestos!$B$3+8)/(1-Supuestos!$B$2)),0)-0.01 | N105: =M105-M105*Supuestos!$B$2-Supuestos!$B$3-2*E105-Supuestos!$B$6 | O105: Sin precio de mercado: precio objetivo | P105: Sin datos de mercado | R105: 16
A106: Daewoo | B106: DW2042FR-09 (FR-09) | D106: 27 | E106: =D106*(1+Supuestos!$B$4) | F106: =E106+Supuestos!$B$5 | G106: =ROUNDUP((F106+Supuestos!$B$3+Supuestos!$B$9)/(1-Supuestos!$B$2),0)-0.01 | H106: =ROUNDUP(MAX((F106+Supuestos!$B$3)/(1-Supuestos!$B$2-Supuestos!$B$8),(F106+Supuestos!$B$3+Supuestos!$B$7)/(1-Supuestos!$B$2)),0)-0.01 | J106: 46.99 | K106: =J106-J106*Supuestos!$B$2-Supuestos!$B$3-F106 | L106: =K106/J106 | M106: =ROUNDUP(MAX(2*J106*0.92,(2*E106+Supuestos!$B$6+Supuestos!$B$3+8)/(1-Supuestos!$B$2)),0)-0.01 | N106: =M106-M106*Supuestos!$B$2-Supuestos!$B$3-2*E106-Supuestos!$B$6 | O106: Sin precio de mercado: precio objetivo | P106: Sin datos de mercado
A107: Fisher & Paykel | B107: FWC1 - 862288 | D107: 75 | E107: =D107*(1+Supuestos!$B$4) | F107: =E107+Supuestos!$B$5 | G107: =ROUNDUP((F107+Supuestos!$B$3+Supuestos!$B$9)/(1-Supuestos!$B$2),0)-0.01 | H107: =ROUNDUP(MAX((F107+Supuestos!$B$3)/(1-Supuestos!$B$2-Supuestos!$B$8),(F107+Supuestos!$B$3+Supuestos!$B$7)/(1-Supuestos!$B$2)),0)-0.01 | J107: 111.99 | K107: =J107-J107*Supuestos!$B$2-Supuestos!$B$3-F107 | L107: =K107/J107 | M107: =ROUNDUP(MAX(2*J107*0.92,(2*E107+Supuestos!$B$6+Supuestos!$B$3+8)/(1-Supuestos!$B$2)),0)-0.01 | N107: =M107-M107*Supuestos!$B$2-Supuestos!$B$3-2*E107-Supuestos!$B$6 | O107: Sin precio de mercado: precio objetivo | P107: Sin datos de mercado | R107: 4
A108: Fisher & Paykel | B108: FWC2 - 862285 | D108: 75 | E108: =D108*(1+Supuestos!$B$4) | F108: =E108+Supuestos!$B$5 | G108: =ROUNDUP((F108+Supuestos!$B$3+Supuestos!$B$9)/(1-Supuestos!$B$2),0)-0.01 | H108: =ROUNDUP(MAX((F108+Supuestos!$B$3)/(1-Supuestos!$B$2-Supuestos!$B$8),(F108+Supuestos!$B$3+Supuestos!$B$7)/(1-Supuestos!$B$2)),0)-0.01 | J108: 111.99 | K108: =J108-J108*Supuestos!$B$2-Supuestos!$B$3-F108 | L108: =K108/J108 | M108: =ROUNDUP(MAX(2*J108*0.92,(2*E108+Supuestos!$B$6+Supuestos!$B$3+8)/(1-Supuestos!$B$2)),0)-0.01 | N108: =M108-M108*Supuestos!$B$2-Supuestos!$B$3-2*E108-Supuestos!$B$6 | O108: Sin precio de mercado: precio objetivo | P108: Sin datos de mercado | R108: 4
A109: Fisher & Paykel | B109: FWC3 - 847200 | D109: 75 | E109: =D109*(1+Supuestos!$B$4) | F109: =E109+Supuestos!$B$5 | G109: =ROUNDUP((F109+Supuestos!$B$3+Supuestos!$B$9)/(1-Supuestos!$B$2),0)-0.01 | H109: =ROUNDUP(MAX((F109+Supuestos!$B$3)/(1-Supuestos!$B$2-Supuestos!$B$8),(F109+Supuestos!$B$3+Supuestos!$B$7)/(1-Supuestos!$B$2)),0)-0.01 | J109: 111.99 | K109: =J109-J109*Supuestos!$B$2-Supuestos!$B$3-F109 | L109: =K109/J109 | M109: =ROUNDUP(MAX(2*J109*0.92,(2*E109+Supuestos!$B$6+Supuestos!$B$3+8)/(1-Supuestos!$B$2)),0)-0.01 | N109: =M109-M109*Supuestos!$B$2-Supuestos!$B$3-2*E109-Supuestos!$B$6 | O109: Sin precio de mercado: precio objetivo | P109: Sin datos de mercado | R109: 4
A110: Fisher & Paykel | B110: FWC4 - 847201 | D110: 75 | E110: =D110*(1+Supuestos!$B$4) | F110: =E110+Supuestos!$B$5 | G110: =ROUNDUP((F110+Supuestos!$B$3+Supuestos!$B$9)/(1-Supuestos!$B$2),0)-0.01 | H110: =ROUNDUP(MAX((F110+Supuestos!$B$3)/(1-Supuestos!$B$2-Supuestos!$B$8),(F110+Supuestos!$B$3+Supuestos!$B$7)/(1-Supuestos!$B$2)),0)-0.01 | J110: 111.99 | K110: =J110-J110*Supuestos!$B$2-Supuestos!$B$3-F110 | L110: =K110/J110 | M110: =ROUNDUP(MAX(2*J110*0.92,(2*E110+Supuestos!$B$6+Supuestos!$B$3+8)/(1-Supuestos!$B$2)),0)-0.01 | N110: =M110-M110*Supuestos!$B$2-Supuestos!$B$3-2*E110-Supuestos!$B$6 | O110: Sin precio de mercado: precio objetivo | P110: Sin datos de mercado | R110: 4
A111: Smart Choice | B111: SCPUREAIRU | D111: 10.89 | E111: =D111*(1+Supuestos!$B$4) | F111: =E111+Supuestos!$B$5 | G111: =ROUNDUP((F111+Supuestos!$B$3+Supuestos!$B$9)/(1-Supuestos!$B$2),0)-0.01 | H111: =ROUNDUP(MAX((F111+Supuestos!$B$3)/(1-Supuestos!$B$2-Supuestos!$B$8),(F111+Supuestos!$B$3+Supuestos!$B$7)/(1-Supuestos!$B$2)),0)-0.01 | J111: 27.99 | K111: =J111-J111*Supuestos!$B$2-Supuestos!$B$3-F111 | L111: =K111/J111 | M111: =ROUNDUP(MAX(2*J111*0.92,(2*E111+Supuestos!$B$6+Supuestos!$B$3+8)/(1-Supuestos!$B$2)),0)-0.01 | N111: =M111-M111*Supuestos!$B$2-Supuestos!$B$3-2*E111-Supuestos!$B$6 | O111: Sin precio de mercado: precio objetivo | P111: Sin datos de mercado | R111: 4
A112: Smart Choice | B112: SCPUREAIR2PK | D112: 13.96 | E112: =D112*(1+Supuestos!$B$4) | F112: =E112+Supuestos!$B$5 | G112: =ROUNDUP((F112+Supuestos!$B$3+Supuestos!$B$9)/(1-Supuestos!$B$2),0)-0.01 | H112: =ROUNDUP(MAX((F112+Supuestos!$B$3)/(1-Supuestos!$B$2-Supuestos!$B$8),(F112+Supuestos!$B$3+Supuestos!$B$7)/(1-Supuestos!$B$2)),0)-0.01 | J112: 30.99 | K112: =J112-J112*Supuestos!$B$2-Supuestos!$B$3-F112 | L112: =K112/J112 | M112: =ROUNDUP(MAX(2*J112*0.92,(2*E112+Supuestos!$B$6+Supuestos!$B$3+8)/(1-Supuestos!$B$2)),0)-0.01 | N112: =M112-M112*Supuestos!$B$2-Supuestos!$B$3-2*E112-Supuestos!$B$6 | O112: Sin precio de mercado: precio objetivo | P112: Sin datos de mercado | R112: 4
A113: Smart Choice | B113: SCPAULTRAII2PK | D113: 13.27 | E113: =D113*(1+Supuestos!$B$4) | F113: =E113+Supuestos!$B$5 | G113: =ROUNDUP((F113+Supuestos!$B$3+Supuestos!$B$9)/(1-Supuestos!$B$2),0)-0.01 | H113: =ROUNDUP(MAX((F113+Supuestos!$B$3)/(1-Supuestos!$B$2-Supuestos!$B$8),(F113+Supuestos!$B$3+Supuestos!$B$7)/(1-Supuestos!$B$2)),0)-0.01 | J113: 29.99 | K113: =J113-J113*Supuestos!$B$2-Supuestos!$B$3-F113 | L113: =K113/J113 | M113: =ROUNDUP(MAX(2*J113*0.92,(2*E113+Supuestos!$B$6+Supuestos!$B$3+8)/(1-Supuestos!$B$2)),0)-0.01 | N113: =M113-M113*Supuestos!$B$2-Supuestos!$B$3-2*E113-Supuestos!$B$6 | O113: Sin precio de mercado: precio objetivo | P113: Sin datos de mercado | R113: 4
A114: Smart Choice | B114: SCWF4CTO | D114: 35.18 | E114: =D114*(1+Supuestos!$B$4) | F114: =E114+Supuestos!$B$5 | G114: =ROUNDUP((F114+Supuestos!$B$3+Supuestos!$B$9)/(1-Supuestos!$B$2),0)-0.01 | H114: =ROUNDUP(MAX((F114+Supuestos!$B$3)/(1-Supuestos!$B$2-Supuestos!$B$8),(F114+Supuestos!$B$3+Supuestos!$B$7)/(1-Supuestos!$B$2)),0)-0.01 | J114: 57.99 | K114: =J114-J114*Supuestos!$B$2-Supuestos!$B$3-F114 | L114: =K114/J114 | M114: =ROUNDUP(MAX(2*J114*0.92,(2*E114+Supuestos!$B$6+Supuestos!$B$3+8)/(1-Supuestos!$B$2)),0)-0.01 | N114: =M114-M114*Supuestos!$B$2-Supuestos!$B$3-2*E114-Supuestos!$B$6 | O114: Sin precio de mercado: precio objetivo | P114: Sin datos de mercado | R114: 4
A115: Smart Choice | B115: SCWFTCTO2 | D115: 35.18 | E115: =D115*(1+Supuestos!$B$4) | F115: =E115+Supuestos!$B$5 | G115: =ROUNDUP((F115+Supuestos!$B$3+Supuestos!$B$9)/(1-Supuestos!$B$2),0)-0.01 | H115: =ROUNDUP(MAX((F115+Supuestos!$B$3)/(1-Supuestos!$B$2-Supuestos!$B$8),(F115+Supuestos!$B$3+Supuestos!$B$7)/(1-Supuestos!$B$2)),0)-0.01 | J115: 57.99 | K115: =J115-J115*Supuestos!$B$2-Supuestos!$B$3-F115 | L115: =K115/J115 | M115: =ROUNDUP(MAX(2*J115*0.92,(2*E115+Supuestos!$B$6+Supuestos!$B$3+8)/(1-Supuestos!$B$2)),0)-0.01 | N115: =M115-M115*Supuestos!$B$2-Supuestos!$B$3-2*E115-Supuestos!$B$6 | O115: Sin precio de mercado: precio objetivo | P115: Sin datos de mercado | R115: 4
A116: Hisense | B116: HX2019FR-A | D116: 36 | E116: =D116*(1+Supuestos!$B$4) | F116: =E116+Supuestos!$B$5 | G116: =ROUNDUP((F116+Supuestos!$B$3+Supuestos!$B$9)/(1-Supuestos!$B$2),0)-0.01 | H116: =ROUNDUP(MAX((F116+Supuestos!$B$3)/(1-Supuestos!$B$2-Supuestos!$B$8),(F116+Supuestos!$B$3+Supuestos!$B$7)/(1-Supuestos!$B$2)),0)-0.01 | J116: 58.99 | K116: =J116-J116*Supuestos!$B$2-Supuestos!$B$3-F116 | L116: =K116/J116 | M116: =ROUNDUP(MAX(2*J116*0.92,(2*E116+Supuestos!$B$6+Supuestos!$B$3+8)/(1-Supuestos!$B$2)),0)-0.01 | N116: =M116-M116*Supuestos!$B$2-Supuestos!$B$3-2*E116-Supuestos!$B$6 | O116: Sin precio de mercado: precio objetivo | P116: Sin datos de mercado | R116: 12

Sheet Supuestos
A1: Supuesto (cámbialo y la hoja se recalcula) | B1: Valor | C1: Qué es
A2: Comisión de PayPal (%) | B2: 0.054 | C2: Comisión por venta. Verifica la de tu cuenta: es una suposición conservadora para una cuenta en Colombia.
A3: Comisión fija por venta (USD) | B3: 0.3 | C3: Cargo fijo por transacción.
A4: Flete y gastos hasta tu depósito (%) | B4: 0.08 | C4: Sobre el precio del proveedor: flete, aranceles, almacenaje. Pon el real.
A5: Envío al cliente, 1 filtro (USD) | B5: 7.5 | C5: Etiqueta promedio nacional (USPS Ground Advantage, menos de 1 lb: unos $5.50 a $8.40 según la zona) + empaque. Si el precio incluye envío gratis, se suma al costo.
A6: Envío al cliente, paquete de 2 (USD) | B6: 9.5 | C6: Etiqueta + empaque.
A7: Ganancia mínima por pedido (USD) | B7: 6 | C7: Para el precio objetivo.
A8: Margen mínimo sobre el precio (%) | B8: 0.15 | C8: Para el precio objetivo.
A9: Ganancia mínima absoluta (USD) | B9: 4 | C9: Para el precio mínimo (el piso).

Sheet Cómo leer
A1: Cómo se calcula el precio
A2: 1. Costo puesto en depósito = precio del proveedor + flete y gastos (%).
A3: 2. Costo + envío al cliente = lo anterior + etiqueta y empaque. El precio de venta incluye envío (envío gratis para el cliente).
A4: 3. Precio mínimo: el menor precio con el que ganas el «piso» (USD) después de la comisión de PayPal.
A5: 4. Precio objetivo: el menor precio que deja al menos la ganancia mínima y el margen mínimo.
A6: 5. Precio de la calle: lo que he visto que cobran otras tiendas por el filtro original (capturas de búsqueda, pueden haber cambiado: verifícalos en Amazon, Walmart y Home Depot antes de publicar).
A7: 6. PRECIO DE VENTA: el objetivo si es competitivo; si no, se iguala al mercado siempre que quede ganancia; si el mercado está casi al precio de costo, no conviene venderlo suelto.
A8: 7. Paquete de 2: descuento de 8 % (mínimo $8 de ganancia): invita a comprar de a 2 y diluye el envío.
A10: Aviso: los precios de mercado son capturas de internet de 2025–2026; cambian a diario. Los costos de flete, aranceles y la comisión de PayPal son supuestos tuyos que debes ajustar en la hoja «Supuestos».
